ox_vox_nns-0.6.1.dist-info/METADATA
ox_vox_nns-0.6.1.dist-info/WHEEL
ox_vox_nns-0.6.1.dist-info/licenses/LICENSE
ox_vox_nns.libs/libgcc_s-b5472b99.so.1
ox_vox_nns/ox_vox_nns.py
ox_vox_nns/__init__.py
ox_vox_nns/py.typed
ox_vox_nns/_ox_vox_nns.cpython-311-i386-linux-musl.so
ox_vox_nns-0.6.1.dist-info/RECORD
