Metadata-Version: 2.3
Name: ox_vox_nns
Version: 0.6.1
Classifier: Programming Language :: Rust
Classifier: Programming Language :: Python :: Implementation :: CPython
Classifier: Programming Language :: Python :: Implementation :: PyPy
Requires-Dist: numpy
License-File: LICENSE
Summary: A hybrid-ish nearest neighbour search implemented in rust using voxels and hashmaps (/dictionaries)
Keywords: nearest,neighbour,pointcloud
Author: Hamish Morgan <ham430@gmail.com>
Author-email: Hamish Morgan <ham430@gmail.com>
Requires-Python: >=3.8
Project-URL: Source Code, https://github.com/hacmorgan/OxVoxNNS
